video_highlight_detection/__init__.py
video_highlight_detection/common.py
video_highlight_detection/video_highlight_detection.py
video_highlight_detection-0.0.1.dist-info/LICENSE
video_highlight_detection-0.0.1.dist-info/METADATA
video_highlight_detection-0.0.1.dist-info/WHEEL
video_highlight_detection-0.0.1.dist-info/entry_points.txt
video_highlight_detection-0.0.1.dist-info/top_level.txt
video_highlight_detection-0.0.1.dist-info/RECORD
