Metadata-Version: 2.1
Name: video-highlight-detection
Version: 0.0.1
Summary: Python Boilerplate contains all the boilerplate you need to create a Python package.
Author-email: Maheen Shoukat <maheenshoukat2015@gmail.com>
License: MIT License
Project-URL: Homepage, https://github.com/Maheen-S6/video-highlight-detection
Keywords: video-highlight-detection
Classifier: Intended Audience :: Developers
Classifier: License :: OSI Approved :: MIT License
Classifier: Natural Language :: English
Classifier: Programming Language :: Python :: 3.8
Classifier: Programming Language :: Python :: 3.9
Classifier: Programming Language :: Python :: 3.10
Classifier: Programming Language :: Python :: 3.11
Classifier: Programming Language :: Python :: 3.12
Requires-Python: >=3.8
License-File: LICENSE
Requires-Dist: numpy
Provides-Extra: all
Requires-Dist: video-highlight-detection[extra] ; extra == 'all'
Provides-Extra: extra
Requires-Dist: pandas ; extra == 'extra'
